Metadata-Version: 1.0
Name: gsn-bnm-distributions
Version: 0.1
Summary: gaussian and binomial probability distributions
Home-page: UNKNOWN
Author: UNKNOWN
Author-email: UNKNOWN
License: UNKNOWN
Platform: UNKNOWN
